pyams_apm/__init__.py
pyams_apm/include.py
pyams_apm/tween.py
pyams_apm/doctests/README.rst
pyams_apm/packages/__init__.py
pyams_apm/packages/chameleon.py
pyams_apm/packages/ldap3.py
pyams_apm/tests/__init__.py
pyams_apm/tests/test_utilsdocs.py
pyams_apm/tests/test_utilsdocstrings.py
pyams_apm-2.0.9.dist-info/LICENSE
pyams_apm-2.0.9.dist-info/METADATA
pyams_apm-2.0.9.dist-info/WHEEL
pyams_apm-2.0.9.dist-info/namespace_packages.txt
pyams_apm-2.0.9.dist-info/top_level.txt
pyams_apm-2.0.9.dist-info/RECORD
