Metadata-Version: 2.1
Name: pyams-apm
Version: 2.0.9
Summary: PyAMS extension package for Elastic APM integration
Home-page: https://pyams.readthedocs.io
Author: Thierry Florac
Author-email: tflorac@ulthar.net
License: ZPL
Keywords: Pyramid PyAMS
Classifier: License :: OSI Approved :: Zope Public License
Classifier: Development Status :: 4 - Beta
Classifier: Programming Language :: Python
Classifier: Framework :: Pyramid
Classifier: Topic :: Software Development :: Libraries :: Python Modules
Requires-Python: >=3.5
License-File: LICENSE
Requires-Dist: setuptools
Requires-Dist: elastic-apm
Requires-Dist: pyramid >=2.0.0
Requires-Dist: importlib-metadata ; python_version < "3.9"
Provides-Extra: test
Requires-Dist: pyramid ; extra == 'test'
Requires-Dist: elastic-apm ; extra == 'test'
